bdapi/__init__.py
bdapi/client.py
bdapi/models.py
protos/bitdrift_public/protobuf/ingest/v1/api_pb2.py
protos/bitdrift_public/protobuf/ingest/v1/api_pb2.pyi
protos/validate/validate_pb2.py
protos/validate/validate_pb2.pyi
bdapi-0.1.2.dist-info/LICENSE
bdapi-0.1.2.dist-info/METADATA
bdapi-0.1.2.dist-info/WHEEL
bdapi-0.1.2.dist-info/entry_points.txt
bdapi-0.1.2.dist-info/RECORD
