Metadata-Version: 2.3
Name: bdapi
Version: 0.1.2
Summary: 
Author: bitdrift, Inc.
Author-email: info@bitdrift.io
Requires-Python: >=3.11
Classifier: Programming Language :: Python :: 3
Classifier: Programming Language :: Python :: 3.11
Classifier: Programming Language :: Python :: 3.12
Classifier: Programming Language :: Python :: 3.13
Requires-Dist: protobuf (>=5.0.0,<6.29.2)
Requires-Dist: requests (>=2.32.3,<3.0.0)
